semchunk/__init__.py
semchunk/py.typed
semchunk/semchunk.py
semchunk-3.2.3.dist-info/METADATA
semchunk-3.2.3.dist-info/WHEEL
semchunk-3.2.3.dist-info/licenses/LICENCE
semchunk-3.2.3.dist-info/RECORD
