Metadata-Version: 2.4
Name: semchunk
Version: 3.2.3
Summary: A fast, lightweight and easy-to-use Python library for splitting text into semantically meaningful chunks.
Project-URL: Homepage, https://github.com/isaacus-dev/semchunk
Project-URL: Documentation, https://github.com/isaacus-dev/semchunk/blob/main/README.md
Project-URL: Issues, https://github.com/isaacus-dev/semchunk/issues
Project-URL: Source, https://github.com/isaacus-dev/semchunk
Author-email: Isaacus <support@isaacus.com>, Umar Butler <umar@umar.au>
License: MIT
License-File: LICENCE
Keywords: chunk,chunker,chunking,chunks,nlp,split,splits,splitter,splitting,text
Classifier: Development Status :: 5 - Production/Stable
Classifier: Intended Audience :: Developers
Classifier: Intended Audience :: Information Technology
Classifier: Intended Audience :: Science/Research
Classifier: License :: OSI Approved :: MIT License
Classifier: Operating System :: OS Independent
Classifier: Programming Language :: Python :: 3.9
Classifier: Programming Language :: Python :: 3.10
Classifier: Programming Language :: Python :: 3.11
Classifier: Programming Language :: Python :: 3.12
Classifier: Programming Language :: Python :: 3.13
Classifier: Programming Language :: Python :: Implementation :: CPython
Classifier: Topic :: Scientific/Engineering :: Artificial Intelligence
Classifier: Topic :: Software Development :: Libraries :: Python Modules
Classifier: Topic :: Text Processing :: General
Classifier: Topic :: Utilities
Classifier: Typing :: Typed
Requires-Python: >=3.9
Requires-Dist: mpire[dill]
Requires-Dist: tqdm
